AUTHORS.rst
CHANGES.rst
COPYING
MANIFEST.in
Makefile
README.rst
setup.py
PySimpleBGC.egg-info/PKG-INFO
PySimpleBGC.egg-info/SOURCES.txt
PySimpleBGC.egg-info/dependency_links.txt
PySimpleBGC.egg-info/entry_points.txt
PySimpleBGC.egg-info/not-zip-safe
PySimpleBGC.egg-info/requires.txt
PySimpleBGC.egg-info/top_level.txt
docs/.gitignore
docs/Makefile
docs/conf.py
docs/index.rst
docs/make.bat
docs/_static/pysimplebgc-reduit.jpg
docs/_static/pysimplebgc.jpg
docs/_templates/sidebarintro.html
docs/_themes/.gitignore
docs/_themes/LICENSE
docs/_themes/README
docs/_themes/flask_theme_support.py
docs/_themes/__pycache__/flask_theme_support.cpython-34.pyc
docs/_themes/flask/layout.html
docs/_themes/flask/relations.html
docs/_themes/flask/theme.conf
docs/_themes/flask/static/flasky.css_t
docs/_themes/flask/static/small_flask.css
docs/_themes/flask_small/layout.html
docs/_themes/flask_small/theme.conf
docs/_themes/flask_small/static/flasky.css_t
pysimplebgc/__init__.py
pysimplebgc/__main__.py
pysimplebgc/compat.py
pysimplebgc/device.py
pysimplebgc/logger.py
pysimplebgc/utils.py