Metadata-Version: 1.1
Name: PySimpleBGC
Version: 0.1
Summary: Communication tools for the Basecam SimpleBGC controller boards
Home-page: https://github.com/LionelDarras/PySimpleBGC
Author: Lionel Darras
Author-email: lionel.darras@mom.fr
License: GNU GPL v3
Platform: UNKNOWN
Classifier: Development Status :: 4 - Beta
Classifier: Intended Audience :: Science/Research
Classifier: Intended Audience :: Developers
Classifier: License :: OSI Approved :: GNU General Public License v3 (GPLv3)
Classifier: Programming Language :: Python :: 3
Classifier: Programming Language :: Python :: 3.2
Classifier: Programming Language :: Python :: 3.4
Classifier: Topic :: Internet
Classifier: Topic :: Utilities
Classifier: Topic :: Software Development :: Libraries :: Python Modules
